[
  {
    "name": "Robert Jones",
    "primary_email": "robert.jones@example.com",
    "primary_phone": "+14155551000",
    "recent_employer": "Consulting Corp",
    "recent_title": "Senior Engineer"
  },
  {
    "name": "Alice Smith",
    "primary_email": "alice.smith@example.com",
    "primary_phone": "+14155551001",
    "recent_employer": "Freelance",
    "recent_title": "Data Scientist"
  },
  {
    "name": "Carol White",
    "primary_email": "carol.white@example.com",
    "primary_phone": "+14155551002",
    "recent_employer": "Msft",
    "recent_title": "Product Manager"
  },
  {
    "name": "Dave Johnson",
    "primary_email": "dave.johnson@example.com",
    "primary_phone": "+14155551003",
    "recent_employer": "Amazon",
    "recent_title": "Senior Devops Engineer"
  },
  {
    "name": "Eve Adams",
    "primary_email": "eve.adams@gmail.com",
    "primary_phone": "+14155551004"
  },
  {
    "name": "Frank Wright",
    "primary_email": "frank.wright@example.com",
    "primary_phone": "+14155551005",
    "recent_employer": "Netflix",
    "recent_title": "Senior Intern"
  },
  {
    "name": "Grace Hopper",
    "primary_email": "grace.hopper@example.com",
    "primary_phone": "+14155551006",
    "recent_employer": "Amazon",
    "recent_title": "Intern"
  },
  {
    "name": "Ivan Q. Drago",
    "primary_email": "ivan.drago@gmail.com",
    "primary_phone": "+14155551008",
    "recent_employer": "Startup Inc.",
    "recent_title": "Senior Engineer"
  },
  {
    "name": "Judy Garland",
    "primary_email": "judy.garland@example.com",
    "primary_phone": "+14155551009",
    "recent_employer": "Netflix",
    "recent_title": "Software Engineer"
  },
  {
    "name": "Ken Thompson",
    "primary_email": "ken.thompson@gmail.com",
    "primary_phone": "+14155551010",
    "recent_employer": "Amazon",
    "recent_title": "Devops Engineer"
  },
  {
    "name": "Mia Wallace",
    "primary_email": "mia.wallace@example.com",
    "primary_phone": "+919811111012",
    "recent_employer": "Freelance",
    "recent_title": "Senior Intern"
  },
  {
    "name": "Noah Carter",
    "primary_email": "noah.carter@example.com",
    "primary_phone": "+14155551013",
    "recent_employer": "Netflix",
    "recent_title": "Devops Engineer"
  },
  {
    "name": "Olivia Pope",
    "primary_email": "olivia.pope@example.com",
    "primary_phone": "+14155551014",
    "recent_employer": "Freelance",
    "recent_title": "Senior Engineer"
  },
  {
    "name": "Quinn W. Fabray",
    "primary_email": "quinn.fabray@gmail.com",
    "primary_phone": "+14155551016",
    "recent_employer": "Apple",
    "recent_title": "Intern"
  },
  {
    "name": "Steve Rogers",
    "primary_email": "steverogers@company.com",
    "primary_phone": "+14155551018",
    "recent_employer": "Consulting Corp",
    "recent_title": "Devops Engineer"
  },
  {
    "name": "Tony Stark",
    "primary_email": "tony.stark@example.com",
    "primary_phone": "+14155551019"
  },
  {
    "name": "Ursula Buffay",
    "primary_email": "ursula.buffay@example.com",
    "primary_phone": "+14155551020",
    "recent_employer": "Apple",
    "recent_title": "Product Manager"
  },
  {
    "name": "Victor Stone",
    "primary_email": "victor.stone@example.com",
    "primary_phone": "+14155551021"
  },
  {
    "name": "Xavier F. Charles",
    "primary_email": "xavier.charles@example.com",
    "primary_phone": "+14155551023",
    "recent_employer": "Netflix",
    "recent_title": "Cto"
  },
  {
    "name": "Yara Shahidi",
    "primary_email": "yara.shahidi@example.com",
    "primary_phone": "+14155551024",
    "recent_employer": "Amazon",
    "recent_title": "Senior Devops Engineer"
  },
  {
    "name": "Heidi Cruz",
    "primary_email": "heidi.cruz@example.com",
    "primary_phone": "+14155551007",
    "recent_employer": "Apple",
    "recent_title": "Intern"
  },
  {
    "name": "Liam Neeson",
    "primary_email": "liam.neeson@example.com",
    "primary_phone": "+14155551011",
    "recent_employer": "Netflix",
    "recent_title": "Senior Senior Engineer"
  },
  {
    "name": "Peter X. Parker",
    "primary_email": "peterparker@company.com",
    "primary_phone": "+14155551015"
  },
  {
    "name": "Rachel X. Green",
    "primary_email": "rachel.green@example.com"
  },
  {
    "name": "Wanda X. Maximoff",
    "primary_email": "wanda.maximoff@example.com",
    "primary_phone": "9811111022",
    "recent_employer": "Startup Inc.",
    "recent_title": "Senior Principal Engineer"
  }
]